pymyq/__init__.py
pymyq/__version__.py
pymyq/account.py
pymyq/api.py
pymyq/const.py
pymyq/device.py
pymyq/errors.py
pymyq/garagedoor.py
pymyq/lamp.py
pymyq/lock.py
pymyq/request.py
pymyq-3.1.6.dist-info/LICENSE
pymyq-3.1.6.dist-info/METADATA
pymyq-3.1.6.dist-info/WHEEL
pymyq-3.1.6.dist-info/top_level.txt
pymyq-3.1.6.dist-info/RECORD
