Metadata-Version: 2.1
Name: pymyq
Version: 3.1.6
Summary: Python package for controlling MyQ-Enabled Garage Door
Home-page: https://github.com/arraylabs/pymyq
Author: Chris Campbell
License: MIT
Platform: UNKNOWN
Classifier: License :: OSI Approved :: MIT License
Classifier: Programming Language :: Python
Classifier: Programming Language :: Python :: 3
Classifier: Programming Language :: Python :: 3.8
Classifier: Programming Language :: Python :: 3.9
Classifier: Programming Language :: Python :: Implementation :: CPython
Classifier: Programming Language :: Python :: Implementation :: PyPy
Requires-Python: >=3.8
License-File: LICENSE
Requires-Dist: aiohttp
Requires-Dist: beautifulsoup4
Requires-Dist: pkce
